custom_button/__init__.py
custom_button/frontend/build/asset-manifest.json
custom_button/frontend/build/bootstrap.min.css
custom_button/frontend/build/index.html
custom_button/frontend/build/precache-manifest.d4307d9a5f9a7fbecedc29ef295b5a54.js
custom_button/frontend/build/service-worker.js
custom_button/frontend/build/static/css/main.9ec91d07.chunk.css
custom_button/frontend/build/static/css/main.9ec91d07.chunk.css.map
custom_button/frontend/build/static/js/2.e519d8d6.chunk.js
custom_button/frontend/build/static/js/2.e519d8d6.chunk.js.LICENSE.txt
custom_button/frontend/build/static/js/2.e519d8d6.chunk.js.map
custom_button/frontend/build/static/js/main.b54fa682.chunk.js
custom_button/frontend/build/static/js/main.b54fa682.chunk.js.map
custom_button/frontend/build/static/js/runtime-main.44d30fc2.js
custom_button/frontend/build/static/js/runtime-main.44d30fc2.js.map
streamlit_custom_button-0.0.3.dist-info/LICENSE
streamlit_custom_button-0.0.3.dist-info/METADATA
streamlit_custom_button-0.0.3.dist-info/WHEEL
streamlit_custom_button-0.0.3.dist-info/top_level.txt
streamlit_custom_button-0.0.3.dist-info/RECORD
